LICENSE
MANIFEST.in
README.md
setup.cfg
setup.py
equiformer_pytorch/__init__.py
equiformer_pytorch/basis.py
equiformer_pytorch/equiformer_pytorch.py
equiformer_pytorch/irr_repr.py
equiformer_pytorch/reversible.py
equiformer_pytorch/utils.py
equiformer_pytorch/version.py
equiformer_pytorch.egg-info/PKG-INFO
equiformer_pytorch.egg-info/SOURCES.txt
equiformer_pytorch.egg-info/dependency_links.txt
equiformer_pytorch.egg-info/requires.txt
equiformer_pytorch.egg-info/top_level.txt
equiformer_pytorch/data/J_dense.pt
tests/test_edges.py
tests/test_equivariance.py