Metadata-Version: 2.1
Name: equiformer-pytorch
Version: 0.5.3
Summary: Equiformer - SE3/E3 Graph Attention Transformer for Molecules and Proteins
Home-page: https://github.com/lucidrains/equiformer-pytorch
Author: Phil Wang
Author-email: lucidrains@gmail.com
License: MIT
Keywords: artificial intelligence,deep learning,transformers,attention mechanism,equivariance,molecules,proteins
Classifier: Development Status :: 4 - Beta
Classifier: Intended Audience :: Developers
Classifier: Topic :: Scientific/Engineering :: Artificial Intelligence
Classifier: License :: OSI Approved :: MIT License
Classifier: Programming Language :: Python :: 3.6
License-File: LICENSE
Requires-Dist: beartype
Requires-Dist: einops>=0.6
Requires-Dist: einx
Requires-Dist: filelock
Requires-Dist: opt-einsum
Requires-Dist: taylor-series-linear-attention>=0.1.4
Requires-Dist: torch>=1.6
